my_framework_2/__init__.py
my_framework_2/cli.py
playwright/__init__.py
playwright/playwright_base.py
playwright/page_objects/__init__.py
playwright/page_objects/example_page.py
playwright/tests/__init__.py
playwright/tests/example_test.py
my_framework_2-1.0.6.dist-info/METADATA
my_framework_2-1.0.6.dist-info/WHEEL
my_framework_2-1.0.6.dist-info/entry_points.txt
my_framework_2-1.0.6.dist-info/top_level.txt
my_framework_2-1.0.6.dist-info/RECORD
