Metadata-Version: 2.1
Name: my_framework_2
Version: 1.0.6
Requires-Dist: playwright
Requires-Dist: pytest
Requires-Dist: behave
